alerting/__init__.py
alerting/clients.py
alerting-0.0.9.3.dist-info/LICENSE
alerting-0.0.9.3.dist-info/METADATA
alerting-0.0.9.3.dist-info/WHEEL
alerting-0.0.9.3.dist-info/top_level.txt
alerting-0.0.9.3.dist-info/RECORD
