Metadata-Version: 2.1
Name: alerting
Version: 0.0.9.3
Summary: Alerting: Easy to Use alerting library for Python
Home-page: https://github.com/sinarezaei/alerting
Author: Sina Rezaei
Author-email: sinarezaei1991@gmail.com
License: MIT
Platform: UNKNOWN
Classifier: Programming Language :: Python :: 3
Classifier: License :: OSI Approved :: MIT License
Classifier: Operating System :: OS Independent
Requires-Python: >=3.6
License-File: LICENSE
Requires-Dist: python-http-client (==3.1.0)
Requires-Dist: typing (==3.6.2)
Requires-Dist: python-telegram-bot (==13.14)
Requires-Dist: sendgrid (==6.0.5)
Requires-Dist: requests (==2.28.1)
